[
    {
        "attribute_set_id": 37,
        "baby_stage": null,
        "brand": 2566,
        "canonical_url": "false",
        "categories": [
            {
                "id": 6367
            },
            {
                "id": 6844
            },
            {
                "id": 9121
            },
            {
                "id": 9655
            },
            {
                "id": 15381
            },
            {
                "id": 15386
            },
            {
                "id": 15418
            },
            {
                "id": 16647
            },
            {
                "id": 17076
            },
            {
                "id": 17086
            },
            {
                "id": 17288
            },
            {
                "id": 18068
            },
            {
                "id": 18129
            },
            {
                "id": 18130
            },
            {
                "id": 18181
            },
            {
                "id": 18287
            },
            {
                "id": 18511
            },
            {
                "id": 18561
            },
            {
                "id": 18562
            },
            {
                "id": 18781
            },
            {
                "id": 18783
            },
            {
                "id": 19110
            },
            {
                "id": 19294
            },
            {
                "id": 19296
            },
            {
                "id": 19321
            },
            {
                "id": 19330
            },
            {
                "id": 19370
            },
            {
                "id": 19371
            },
            {
                "id": 19375
            },
            {
                "id": 19433
            },
            {
                "id": 19437
            },
            {
                "id": 19482
            },
            {
                "id": 19489
            },
            {
                "id": 19569
            },
            {
                "id": 19578
            },
            {
                "id": 19635
            },
            {
                "id": 19651
            },
            {
                "id": 19653
            },
            {
                "id": 19764
            }
        ],
        "color": null,
        "configurable_color": null,
        "country_of_manufacture": null,
        "created_at": "2022-06-18 14:26:22",
        "crosssell_products": [],
        "department": "430 - BELLEZA                                 ",
        "description": {
            "html": "LA ROCHE POSAY Kit Protector Solar para Pieles Normales a Mixtas 100 ml"
        },
        "dropship_vendor_id": null,
        "gift_message_available": null,
        "id": 2689779,
        "image": {
            "disabled": null,
            "label": "Kit Protector Solar para Pieles Normales a Mixtas 100 ml",
            "position": null,
            "url": "https://www.heb.com.mx/media/catalog/product/cache/90802a3c5b1f86db2f3f2b7af0d33806/8/6/866781_1_image-1655780252.jpg"
        },
        "is_ahorramas": null,
        "is_comboloco": null,
        "is_gift_message": null,
        "is_gluten_free": null,
        "is_hebhit": 0,
        "is_horecas_sale": 0,
        "is_internet_exclusive": 0,
        "is_lactosa_free": null,
        "is_low_carbohydrates": null,
        "is_low_fat": null,
        "is_natural": null,
        "is_organic": null,
        "is_presale": null,
        "is_promo_applied": null,
        "is_reduced": 0,
        "is_returnable": "2",
        "is_save_more_applied": null,
        "is_sugar_free": null,
        "is_vegetarian": null,
        "manufacturer": null,
        "material_type": null,
        "maxorderquantity": "100",
        "media_gallery": [
            {
                "disabled": false,
                "label": "1",
                "position": 1,
                "url": "https://www.heb.com.mx/media/catalog/product/cache/90802a3c5b1f86db2f3f2b7af0d33806/8/6/866781_1_image-1655780252.jpg"
            },
            {
                "disabled": true,
                "label": "2",
                "position": 1,
                "url": "https://www.heb.com.mx/media/catalog/product/cache/90802a3c5b1f86db2f3f2b7af0d33806/8/6/866781_1_thumbnail-1655780252.jpg"
            },
            {
                "disabled": true,
                "label": "3",
                "position": 1,
                "url": "https://www.heb.com.mx/media/catalog/product/cache/90802a3c5b1f86db2f3f2b7af0d33806/8/6/866781_1_small-1655780252.jpg"
            },
            {
                "disabled": false,
                "label": "7",
                "position": 1,
                "url": "https://www.heb.com.mx/media/catalog/product/cache/90802a3c5b1f86db2f3f2b7af0d33806/8/6/866781_image-1655780252.jpg"
            },
            {
                "disabled": true,
                "label": "2",
                "position": 1,
                "url": "https://www.heb.com.mx/media/catalog/product/cache/90802a3c5b1f86db2f3f2b7af0d33806/8/6/866781_thumbnail-1655780252.jpg"
            },
            {
                "disabled": true,
                "label": "3",
                "position": 1,
                "url": "https://www.heb.com.mx/media/catalog/product/cache/90802a3c5b1f86db2f3f2b7af0d33806/8/6/866781_small-1655780252.jpg"
            },
            {
                "disabled": false,
                "label": "4",
                "position": 1,
                "url": "https://www.heb.com.mx/media/catalog/product/cache/90802a3c5b1f86db2f3f2b7af0d33806/8/6/866781_4_image-1655780252.jpg"
            },
            {
                "disabled": false,
                "label": "5",
                "position": 1,
                "url": "https://www.heb.com.mx/media/catalog/product/cache/90802a3c5b1f86db2f3f2b7af0d33806/8/6/866781_2_image-1655780252.jpg"
            },
            {
                "disabled": false,
                "label": "6",
                "position": 1,
                "url": "https://www.heb.com.mx/media/catalog/product/cache/90802a3c5b1f86db2f3f2b7af0d33806/8/6/866781_3_image-1655780252.jpg"
            }
        ],
        "meta_description": "LA ROCHE POSAY Kit Protector Solar para Pieles Normales a Mixtas BELLEZA                                  DERMATOLOGIA                             BLOQUEADORES                            ",
        "meta_keyword": "0",
        "meta_title": "Kit Protector Solar para Pieles Normales a Mixtas 100 ml",
        "minorderquantity": "1",
        "name": "Kit Protector Solar para Pieles Normales a Mixtas 100 ml",
        "new_from_date": null,
        "new_to_date": null,
        "nuevo_etiquetado": null,
        "only_x_left_in_stock": null,
        "options_container": "container2",
        "orderincrement": "1",
        "presale_available_from": null,
        "price_range": {
            "maximum_price": {
                "discount": {
                    "amount_off": 0,
                    "percent_off": 0
                },
                "final_price": {
                    "currency": "MXN",
                    "value": 587
                },
                "fixed_product_taxes": [],
                "regular_price": {
                    "currency": "MXN",
                    "value": 587
                }
            },
            "minimum_price": {
                "discount": {
                    "amount_off": 0,
                    "percent_off": 0
                },
                "final_price": {
                    "currency": "MXN",
                    "value": 587
                },
                "fixed_product_taxes": [],
                "regular_price": {
                    "currency": "MXN",
                    "value": 587
                }
            }
        },
        "price_tiers": [],
        "product_links": [],
        "product_specs": null,
        "product_video": null,
        "promotion_type": "429",
        "purchase_units": "each",
        "related_products": [],
        "screen_size": null,
        "short_description": {
            "html": "LA ROCHE POSAY Kit Protector Solar para Pieles Normales a Mixtas 100 ml"
        },
        "sku": "866781",
        "small_image": {
            "disabled": null,
            "label": "Kit Protector Solar para Pieles Normales a Mixtas 100 ml",
            "position": null,
            "url": "https://www.heb.com.mx/media/catalog/product/cache/90802a3c5b1f86db2f3f2b7af0d33806/8/6/866781_1_small-1655780252.jpg"
        },
        "snipecarbaware": null,
        "snipegfv": null,
        "snipegolocal": null,
        "snipegsf": null,
        "snipehh": null,
        "snipels": null,
        "snipelsat": null,
        "snipenew": null,
        "snipesugfree": null,
        "snipevegan": null,
        "sold_by_type": "each",
        "special_from_date": "2022-06-23 00:00:00",
        "special_price": 575,
        "special_to_date": "2022-06-23 12:00:00",
        "stock_status": "IN_STOCK",
        "swatch_image": null,
        "thumbnail": {
            "disabled": null,
            "label": "Kit Protector Solar para Pieles Normales a Mixtas 100 ml",
            "position": null,
            "url": "https://www.heb.com.mx/media/catalog/product/cache/90802a3c5b1f86db2f3f2b7af0d33806/8/6/866781_1_thumbnail-1655780252.jpg"
        },
        "tiempo_entrega": null,
        "unit_weight": null,
        "uomcode": "pz",
        "uomqty": "0",
        "upc": "7509552805864",
        "updated_at": "2022-06-25 03:32:00",
        "upsell_products": [],
        "url_key": "la-roche-posay-kit-protector-solar-pieles-normales-mixtas-100-ml-866781",
        "url_rewrites": [],
        "url_suffix": ".html",
        "vendor_name": null,
        "winetype": null,
        "position": 1,
        "brandName": "LA ROCHE POSAY"
    }
]